[{"uri": "http://www.wikidata.org/entity/Q9531", "id": "Q9531", "label": "British Broadcasting Corporation", "desc": "British public service broadcaster"}, {"uri": "http://www.wikidata.org/entity/Q216108", "id": "Q216108", "label": "BBC Two", "desc": "television channel operated by the BBC"}, {"uri": "http://www.wikidata.org/entity/Q795598", "id": "Q795598", "label": "BBC Radio 4", "desc": "British national radio station"}, {"uri": "http://www.wikidata.org/entity/Q1160945", "id": "Q1160945", "label": "BBC News", "desc": "news division of the publicly funded British Broadcasting Corporation"}, {"uri": "http://www.wikidata.org/entity/Q687427", "id": "Q687427", "label": "BBC Three", "desc": "Terrestrial television channel operated by the BBC until 2016"}]